dpm_srm.cpython-39-darwin.so
dpm_srm-0.1.7.dist-info/RECORD
dpm_srm-0.1.7.dist-info/LICENSE
dpm_srm-0.1.7.dist-info/WHEEL
dpm_srm-0.1.7.dist-info/top_level.txt
dpm_srm-0.1.7.dist-info/METADATA
