Metadata-Version: 2.1
Name: dpm_srm
Version: 0.1.7
Summary: Statistical Region Merging Segmentation
Author: Digital Porous Media
Author-email: Digital Porous Media <bcchang@utexas.edu>
License: BSD License
Project-URL: Homepage, https://github.com/digital-porous-media/
Project-URL: Repository, https://github.com/digital-porous-media/dpm_srm
Project-URL: Issues, https://github.com/digital-porous-media/dpm_srm/issues
Classifier: Development Status :: 2 - Pre-Alpha
Classifier: Intended Audience :: Science/Research
Classifier: License :: OSI Approved :: BSD License
Classifier: Programming Language :: Python :: 3
Classifier: Programming Language :: Python :: 3.8
Classifier: Programming Language :: Python :: 3.9
Classifier: Programming Language :: Python :: 3.10
Classifier: Programming Language :: Python :: 3.11
Classifier: Programming Language :: Python :: 3.12
Classifier: Programming Language :: Python :: 3.13
Requires-Python: >=3.8
License-File: LICENSE
Requires-Dist: numpy
